src/voyagercpu/__init__.py
src/voyagercpu/cpu.py
src/voyagercpu/decoder.py
src/voyagercpu/example.py
src/voyagercpu/ram.py
src/voyagercpu/utils.py
voyager_cpu-0.2.4.dist-info/METADATA
voyager_cpu-0.2.4.dist-info/WHEEL
voyager_cpu-0.2.4.dist-info/licenses/LICENSE.md
voyager_cpu-0.2.4.dist-info/RECORD
