Metadata-Version: 2.1
Name: voyager-cpu
Version: 0.2.4
Summary: A simple 32-bit RISC-V CPU emulator
Project-URL: Homepage, https://github.com/cgshep/voyager-cpu
Project-URL: Bug Tracker, https://github.com/cgshep/voyager-cpu/issues
Author-email: Carlton Shepherd <carlton@linux.com>
License-Expression: MIT
License-File: LICENSE.md
Classifier: Development Status :: 2 - Pre-Alpha
Classifier: Intended Audience :: Developers
Classifier: Intended Audience :: Science/Research
Classifier: License :: OSI Approved :: MIT License
Classifier: Operating System :: OS Independent
Classifier: Programming Language :: Assembly
Classifier: Programming Language :: Python :: 3
Classifier: Topic :: System :: Emulators
Requires-Python: >=3.7
Requires-Dist: elftools>=0.29
Provides-Extra: tests
Requires-Dist: pytest>=7.0; extra == 'tests'
